wxve/__init__.py
wxve/stock.py
wxve/stockset.py
wxve-0.0.17.dist-info/LICENSE
wxve-0.0.17.dist-info/METADATA
wxve-0.0.17.dist-info/WHEEL
wxve-0.0.17.dist-info/top_level.txt
wxve-0.0.17.dist-info/RECORD
