Metadata-Version: 2.1
Name: wxve
Version: 0.0.17
Summary: A stock analysis package in Python that equips objects with the information required to streamline operations.
Home-page: https://github.com/AG3NTZ3R0/wxve
Author: Brandon J. Lacy
Author-email: Z3R0@duck.com
License: UNKNOWN
Project-URL: Bug Tracker, https://github.com/AG3NTZ3R0/wxve/issues
Platform: UNKNOWN
Classifier: Programming Language :: Python :: 3
Classifier: License :: OSI Approved :: MIT License
Classifier: Operating System :: OS Independent
Requires-Python: >=3.6
License-File: LICENSE
Requires-Dist: pandas
Requires-Dist: plotly
Requires-Dist: yh-finance
